{
	"quests": [
		{
			"id": "meatballs",
			"item": "minecraft:cooked_beef",
			"rand": 0.4,
			"baseprofit": 5,
			"baseqty": 4,
			"multqty": 1.45,
			"levelscale": 0.5
		},
		{
			"id": "spellbind",
			"item": "botania:spellcloth",
			"rand": 0.4,
			"baseprofit": 30,
			"baseqty": 1,
			"multqty": 1,
			"levelscale": 0.5
		},
		{
			"id": "pipes",
			"item": "buildcrafttransport:pipe_gold_item",
			"rand": 0.1,
			"baseprofit": 8,
			"baseqty": 4,
			"multqty": 1.7,
			"levelscale": 0.5
		},
		{
			"id": "glass",
			"item": "minecraft:glass",
			"rand": 0.4,
			"baseprofit": 2,
			"baseqty": 10,
			"multqty": 1.45,
			"levelscale": 0.8
		},
		{
			"id": "zombie",
			"item": "botania:virus",
			"rand": 0.2,
			"baseprofit": 16,
			"baseqty": 2,
			"multqty": 1.8,
			"levelscale": 0.8
		},
		{
			"id": "batteries",
			"item": "contenttweaker:cobalt_battery",
			"rand": 0.1,
			"baseprofit": 11,
			"baseqty": 4,
			"multqty": 1.45,
			"levelscale": 0.5
		},
		{
			"id": "column",
			"item": "thermalexpansion:augment:368",
			"rand": 0.1,
			"baseprofit": 12,
			"baseqty": 1,
			"multqty": 1.45,
			"levelscale": 0.5
		},
		{
			"id": "drill",
			"item": "factorytech:oredrill",
			"rand": 0.1,
			"baseprofit": 14,
			"baseqty": 8,
			"multqty": 1.45,
			"levelscale": 0.5
		},
		{
			"id": "terraech",
			"item": "botania:terrasword",
			"rand": 0.1,
			"baseprofit": 11,
			"baseqty": 1,
			"multqty": 1,
			"levelscale": 0.5
		},
		{
			"id": "belt",
			"item": "botania:supertravelbelt",
			"rand": 0.1,
			"baseprofit": 22,
			"baseqty": 1,
			"multqty": 1,
			"levelscale": 0.5
		},
		{
			"id": "mindpower",
			"item": "incorporeal:cygnus_spark",
			"rand": 0.1,
			"baseprofit": 3,
			"baseqty": 3,
			"multqty": 1.6,
			"levelscale": 0.8
		},
		{
			"id": "upgrade",
			"item": "thermalexpansion:upgrade:128",
			"rand": 0.1,
			"baseprofit": 5,
			"baseqty": 3,
			"multqty": 1.6,
			"levelscale": 0.8
		},
		{
			"id": "lumium",
			"item": "thermalfoundation:material:294",
			"rand": 0.7,
			"baseprofit": 9,
			"baseqty": 3,
			"multqty": 1.6,
			"levelscale": 0.8
		},
		{
			"id": "mindpower",
			"item": "incorporeal:cygnus_spark",
			"rand": 0.1,
			"baseprofit": 3,
			"baseqty": 3,
			"multqty": 1.6,
			"levelscale": 0.8
		},
		{
			"id": "clones",
			"item": "botania:avatar",
			"rand": 0.4,
			"baseprofit": 7,
			"baseqty": 2,
			"multqty": 1.9,
			"levelscale": 0.8
		},
		{
			"id": "mining",
			"item": "opencomputers:card:1",
			"rand": 0.1,
			"baseprofit": 10,
			"baseqty": 2,
			"multqty": 1.4,
			"levelscale": 0.8
		},
		{
			"id": "rotten",
			"item": "minecraft:rotten_flesh",
			"rand": 0.1,
			"baseprofit": 2,
			"baseqty": 2,
			"multqty": 1.4,
			"levelscale": 0.8
		},
		{
			"id": "travel",
			"item": "botania:relay",
			"rand": 0.1,
			"baseprofit": 5,
			"baseqty": 1,
			"multqty": 1,
			"levelscale": 0.8
		},
		{
			"id": "hehe",
			"item": "extendedcrafting:material:32",
			"rand": 0.8,
			"baseprofit": 1000,
			"baseqty": 12,
			"multqty": 1.8,
			"levelscale": 0.2
		}
	]
}